deepfriedmarshmallow/__init__.py
deepfriedmarshmallow/compat.py
deepfriedmarshmallow/import_patch.py
deepfriedmarshmallow/jit/__init__.py
deepfriedmarshmallow/jit/plugins/__init__.py
deepfriedmarshmallow/jit/plugins/constant_plugin.py
deepfriedmarshmallow/jit/plugins/datetime_plugin.py
deepfriedmarshmallow/jit/plugins/decimal_plugin.py
deepfriedmarshmallow/jit/plugins/dict_plugin.py
deepfriedmarshmallow/jit/plugins/enum_plugin.py
deepfriedmarshmallow/jit/plugins/list_plugin.py
deepfriedmarshmallow/jit/plugins/nested_plugin.py
deepfriedmarshmallow/jit/plugins/raw_plugin.py
deepfriedmarshmallow/jit/plugins/tuple_plugin.py
deepfriedmarshmallow/log.py
deepfriedmarshmallow/mixin.py
deepfriedmarshmallow/patch.py
deepfriedmarshmallow/serializer.py
deepfriedmarshmallow/tests_dummy_plugin.py
deepfriedmarshmallow/utils.py
deepfriedmarshmallow-1.1.2.dist-info/LICENSE
deepfriedmarshmallow-1.1.2.dist-info/METADATA
deepfriedmarshmallow-1.1.2.dist-info/WHEEL
deepfriedmarshmallow-1.1.2.dist-info/RECORD
