Metadata-Version: 2.1
Name: DeepFriedMarshmallow
Version: 1.1.2
Summary: A plug-and-play JIT implementation for Marshmallow to speed up data serialization and deserialization
Home-page: https://github.com/mLupine/DeepFriedMarshmallow
License: Apache-2.0
Keywords: serialization,rest,json,api,marshal,marshalling,deserialization,validation,schema
Author: Maciej Wilczynski
Author-email: oss@lupin.rocks
Requires-Python: >=3.11,<4.0.0
Classifier: Development Status :: 5 - Production/Stable
Classifier: Intended Audience :: Developers
Classifier: License :: OSI Approved :: Apache Software License
Classifier: Programming Language :: Python :: 3
Classifier: Programming Language :: Python :: 3.11
Classifier: Programming Language :: Python :: 3.12
Classifier: Programming Language :: Python :: 3.13
Classifier: Programming Language :: Python :: Implementation :: CPython
Classifier: Programming Language :: Python :: Implementation :: PyPy
Requires-Dist: attrs (>=17.1.0)
Requires-Dist: marshmallow (>=3.13.0,<5.0.0)
Requires-Dist: six (>=1.16.0,<2.0.0)
